{
  "type": "minecraft:block",
  "pools": [
    {
      "bonus_rolls": 0.0,
      "entries": [
        {
          "type": "minecraft:item",
          "name": "aspects:giant_clam"
        },
        {
          "type": "minecraft:item",
          "conditions": [
            {
              "chance": 0.1,
              "condition": "minecraft:random_chance"
            }
          ],
          "name": "aspects:pink_pearl"
        },
        {
          "type": "minecraft:item",
          "conditions": [
            {
              "chance": 0.01,
              "condition": "minecraft:random_chance"
            }
          ],
          "name": "aspects:gold_pearl"
        }
      ],
      "rolls": 1.0
    }
  ],
  "random_sequence": "aspects:blocks/giant_clam"
}